{
  "name": "Citrus Finance on Kroma Sepolia",
  "version": {
    "major": 1,
    "minor": 0,
    "patch": 0
  },
  "timestamp": "2025-10-06T22:06:52.023Z",
  "tokens": [
    {
      "chainId": 2358,
      "address": "0x4200000000000000000000000000000000000001",
      "name": "Wrapped Ether",
      "symbol": "WETH",
      "decimals": 18,
      "logoURI": "https://etherscan.io/token/images/weth_28.png?v=2",
      "tags": []
    },
    {
      "name": "Sepolia Ether",
      "symbol": "ETH",
      "decimals": 18,
      "address": "0xEeeeeEeeeEeEeeEeEeEeeEEEeeeeEeeeeeeeEEeE",
      "chainId": 2358,
      "logoURI": "https://raw.githubusercontent.com/TalismanSociety/chaindata/main/assets/chains/known/kroma.svg",
      "extensions": {
        "wrapped": "0x4200000000000000000000000000000000000001"
      },
      "tags": [
        "Top"
      ]
    }
  ]
}