{
  "name": "Citrus Finance on Orderly",
  "version": {
    "major": 1,
    "minor": 0,
    "patch": 0
  },
  "timestamp": "2024-12-14T23:40:49.694Z",
  "tokens": [
    {
      "chainId": 291,
      "address": "0x4200000000000000000000000000000000000006",
      "name": "Wrapped Ether",
      "symbol": "WETH",
      "decimals": 18,
      "logoURI": "https://assets.citrus.finance/token-logos/291/0x4200000000000000000000000000000000000006.png",
      "tags": [],
      "extensions": {
        "cacheHash": "14afc9a568891be03e2330f9a7646a7c"
      }
    }
  ]
}